cosinnus_message/__init__.py
cosinnus_message/admin.py
cosinnus_message/apps.py
cosinnus_message/conf.py
cosinnus_message/cosinnus_app.py
cosinnus_message/cron.py
cosinnus_message/forms.py
cosinnus_message/models.py
cosinnus_message/postman_urls.py
cosinnus_message/urls.py
cosinnus_message/views.py
cosinnus_message/locale/de/LC_MESSAGES/django.mo
cosinnus_message/locale/de/LC_MESSAGES/django.po
cosinnus_message/locale/en/LC_MESSAGES/django.mo
cosinnus_message/locale/en/LC_MESSAGES/django.po
cosinnus_message/locale/fr/LC_MESSAGES/django.mo
cosinnus_message/locale/fr/LC_MESSAGES/django.po
cosinnus_message/locale/ru/LC_MESSAGES/django.mo
cosinnus_message/locale/ru/LC_MESSAGES/django.po
cosinnus_message/locale/uk/LC_MESSAGES/django.mo
cosinnus_message/locale/uk/LC_MESSAGES/django.po
cosinnus_message/management/__init__.py
cosinnus_message/management/commands/__init__.py
cosinnus_message/management/commands/fake_process_direct_reply_mails.py
cosinnus_message/management/commands/process_direct_reply_mails.py
cosinnus_message/migrations/0001_initial.py
cosinnus_message/migrations/__init__.py
cosinnus_message/static/css/message.css
cosinnus_message/templates/cosinnus_message/attachments_form.html
cosinnus_message/templates/cosinnus_message/base.html
cosinnus_message/templates/cosinnus_message/email_direct_reply_failed.txt
cosinnus_message/templates/cosinnus_message/message_attachments.html
cosinnus_message/templates/postman/archives.html
cosinnus_message/templates/postman/base.html
cosinnus_message/templates/postman/base_folder.html
cosinnus_message/templates/postman/base_write.html
cosinnus_message/templates/postman/email_user.txt
cosinnus_message/templates/postman/email_user_subject.txt
cosinnus_message/templates/postman/email_visitor.txt
cosinnus_message/templates/postman/email_visitor_subject.txt
cosinnus_message/templates/postman/inbox.html
cosinnus_message/templates/postman/inc_subject_ex.html
cosinnus_message-0.6.dev20180515152501.dist-info/DESCRIPTION.rst
cosinnus_message-0.6.dev20180515152501.dist-info/METADATA
cosinnus_message-0.6.dev20180515152501.dist-info/RECORD
cosinnus_message-0.6.dev20180515152501.dist-info/WHEEL
cosinnus_message-0.6.dev20180515152501.dist-info/metadata.json
cosinnus_message-0.6.dev20180515152501.dist-info/top_level.txt
