Metadata-Version: 2.0
Name: cosinnus-message
Version: 0.6.dev20180515152501
Summary: cosinnus user messaging application
Home-page: UNKNOWN
Author: Sinnwerkstatt Medienagentur GmbH Berlin
Author-email: web@Sinnwerkstatt.com
License: UNKNOWN
Platform: UNKNOWN
Classifier: Development Status :: 3 - Alpha
Classifier: Environment :: Web Environment
Classifier: Intended Audience :: Developers
Classifier: Operating System :: OS Independent
Classifier: Programming Language :: Python
Classifier: Programming Language :: Python :: 2
Classifier: Programming Language :: Python :: 2.7
Classifier: Programming Language :: Python :: 3
Classifier: Programming Language :: Python :: 3.2
Classifier: Programming Language :: Python :: 3.3
Classifier: Framework :: Django
Requires-Dist: cosinnus (>=0.4.2.dev0)
Requires-Dist: django-mailbox (==4.5.4)
